ALU.v
`default_nettype none                                              
                                               
module ALU #(                                                      
    parameter W = 8,                                               
    parameter CMDWD = 4                                            
) (                                                                
    CLK, RST, INP_VALID, MODE, CMD, CE, OPA, OPB, CIN, ERR, RES, OFLOW, COUT, G, L, E
);

localparam RW = $clog2(W);
                                                                   
input wire RST;
input wire CLK;
input wire CE;
input wire MODE;
input wire CIN;                                   
input wire signed [W-1:0] OPA, OPB;
input wire [CMDWD-1:0] CMD;
input wire [1:0] INP_VALID;
output reg signed [(2*W)-1:0] RES;
output reg COUT;
output reg OFLOW;
output reg G, L, E;
output reg ERR;
                                                                   
reg signed [(2*W)-1:0] res;                                        
reg                 cout, oflow;                                   
reg                 g, l, e;                                       
reg                 err;                                           
reg                 C;
reg [1:0]           IV;                       
reg [W-1:0]         A, B;                                   
reg signed [W-1:0]  SA, SB;

reg mul_done;
                                                                   
always @(posedge CLK or posedge RST) begin                         
    if(RST) begin                                                  
        RES         <= 0;
        COUT        <= 0;
        OFLOW       <= 0;
        {G, L, E}   <= 0;
        ERR         <= 0;
        A           <= 0;
        B           <= 0;
        C           <= 0;
        SA          <= 0;
        SB          <= 0;
    end else begin
      	A           <= OPA;
        B           <= OPB;
        C           <= CIN;
        IV          <= INP_VALID;
        SA          <= OPA;
        SB          <= OPB;
      if(CE) begin
        RES         <= res;
        COUT        <= cout;
        OFLOW       <= oflow;
        ERR         <= err;
        {G, L, E}   <= {g, l, e};
      end
    end
end

always @(*) begin
    res = 0;
    cout = 0;
    oflow = cout;
    err = 0;
    {g, l, e} = 0;
  if(MODE) begin
        case(CMD)
            0: begin
                {cout, res[W-1:0], err} = (IV == 2'b11) ? {A + B, 1'b0} : 1;
            end
            1: begin
                {cout, res[W-1:0], err} = (IV == 2'b11) ? {A - B, 1'b0} : 1;
            end
            2: begin
                {cout, res[W-1:0], err} = (IV == 2'b11) ? {A + B + C, 1'b0} : 1;
            end
            3: begin
                {cout, res[W-1:0], err} = (IV == 2'b11) ? {A - B - C, 1'b0} : 1;
            end
            4: begin
                {cout, res[W-1:0], err} = (IV[0] == 1'b1) ? {A + 1'b1, 1'b0} : 1;
            end
            5: begin
                {cout, res[W-1:0], err} = (IV[0] == 1'b1) ? {A - 1'b1, 1'b0} : 1;
            end
            6: begin
                {cout, res[W-1:0], err} = (IV[1] == 1'b1) ? {B + 1'b1, 1'b0} : 1;
            end
            7: begin
                {cout, res[W-1:0], err} = (IV[1] == 1'b1) ? {B - 1'b1, 1'b0} : 1;
            end
            8: begin
                {g, l, e, err}  = (IV == 2'b11) ? {A > B, A < B, A == B, 1'b0} : 1;
            end
            9: begin
                {cout, res, err} = (IV == 2'b11) ? {(A + 1'b1) * (B + 1'b1), 1'b0} : 1;
            end
            10: begin
                {cout, res, err} = (IV == 2'b11) ? {(A << 1'b1) * B, 1'b0} : 1;
            end
            11: begin
                if(IV == 2'b11) begin
                    {cout, res[W-1:0]} = SA + SB;
                    {g, l, e}  = {SA > SB, SA < SB, SA == SB};
                    oflow = (~SA[W-1] & ~SB[W-1] & res[W-1]) | (SA[W-1] & SA[W-1] & ~res[W-1]);
                end else begin
                    {cout, res, g, l, e, oflow, err} = 1;
                end
            end
            12: begin
                if(IV == 2'b11) begin
                  {cout, res[W-1:0]} = SA - SB;
                  {g, l, e} = {SA > SB, SA < SB, SA == SB};
                  oflow = (SA[W-1] ^ SB[W-1]) & (res[W-1] ^ SA[W-1]);
                end else begin
                  {cout, res, g, l, e, oflow, err} = 1;
                end
            end
            default: res = 0;
        endcase
    end else begin
        case(CMD)
            0: begin
                {res, err} = (IV == 2'b11) ? {A & B, 1'b0} : 1;
            end
            1: begin
                {res, err} = (IV == 2'b11) ? {~(A & B), 1'b0} : 1;
            end
            2: begin
                {res, err} = (IV == 2'b11) ? {A | B, 1'b0} : 1;
            end
            3: begin
                {res, err} = (IV == 2'b11) ? {~(A | B), 1'b0} : 1;
            end
            4: begin
                {res, err} = (IV == 2'b11) ? {A ^ B, 1'b0} : 1;
            end
            5: begin
                {res, err} = (IV == 2'b11) ? {~(A ^ B), 1'b0} : 1;
            end
            6: begin
                {res, err} = (IV[0] == 1'b1) ? {~A, 1'b0} : 1;
            end
            7: begin
                {res, err} = (IV[1] == 1'b1) ? {~B, 1'b0} : 1;
            end
            8: begin
                {res, err} = (IV[0] == 1'b1) ? {A >> 1, 1'b0} : 1;
            end
            9: begin
                {res, err} = (IV[0] == 1'b1) ? {A << 1, 1'b0} : 1;
            end
            10: begin
                {res, err} = (IV[1] == 1'b1) ? {B >> 1, 1'b0} : 1;
            end
            11: begin
                {res, err} = (IV[1] == 1'b1) ? {B << 1, 1'b0} : 1;
            end
            12: begin
                if(IV == 2'b11 && ~|B[W-1:RW]) begin
                    res = (A << B[RW-1:0] | A >> (W - B[RW-1:0])) & {W{1'b1}};
                    // res = ({A, A} << B[RW-1:0]) >> W;
                end else begin
                  {res, err} = 1;
                end
            end
            13: begin
                if(IV == 2'b11 && ~|B[W-1:RW]) begin
                    res = (A >> B[RW-1:0] | A << (W - B[RW-1:0])) & {W{1'b1}};
                    // res = {A, A} >> B[RW-1:0];
                end else begin
                  {res, err} = 1;
                end
            end
            default: res = 0;
        endcase
    end
end
endmodule

tb_ALU.v
`include "ALU.v"

`define WIDTH 8
`define VALID_M 2
`define OPERATION 4

module tb;
    reg CLK;
    reg RST;
    reg [`VALID_M-1:0] INP_VALID;
	reg  MODE;
    reg [`OPERATION-1:0] CMD;
	reg CE;
    reg [`WIDTH-1:0] OPA;
    reg [`WIDTH-1:0] OPB;
    reg CIN;
    wire ERR;
    wire [2*`WIDTH-1:0] RES;
	wire OFLOW;
	wire COUT;
	wire G;
	wire L;
	wire E;
    integer i;
 
  ALU dut(CLK,RST,INP_VALID,MODE,CMD,CE,OPA,OPB,CIN, ERR, RES,OFLOW,COUT,G,L,E);
 
 
  initial begin
    CLK=1'b0;
    forever #5 CLK=~CLK;
  end
 
  task arithmetic_inputs;
  begin
    MODE = 1'b1;
    CE=1'b1;
    RST = 1'b0;
    INP_VALID = 2'b11;
    OPA = 10;
    OPB = 5;
    @(posedge CLK);
    for(i=0;i<14;i=i+1) begin
        // OPA = $urandom();
        // OPB = $urandom();
        CMD = i;
        CIN = 1;
        @(posedge CLK);
        if(i == 9) begin
            OPA = 4;
            OPB = 5;
            @(posedge CLK);
            @(posedge CLK); 
        end else if(i == 10) begin
          OPA = 10;
          OPB = 3;
          @(posedge CLK);
          @(posedge CLK);
        end
    end
  end
  endtask
 
   task logic_inputs;
   begin
    MODE = 1'b0;
    CE=1'b1;
    RST = 1'b0;
    INP_VALID = 2'b11;
 
    for(i=0;i<14;i=i+1) begin
//       OPA = $urandom();
      OPA = 10;
//       OPB = $urandom();
      OPB = 5;
      CMD = i;
      CIN = 1;
      @(posedge CLK);
    end
 end
  endtask
 
  task reset;
  begin
    RST=1'b1;
    repeat(2)
      @(posedge CLK);
 
    RST=1'b0;
  end
  endtask
 
  initial begin
    reset;
    arithmetic_inputs;
    logic_inputs;
    repeat(3)
      @(posedge CLK);
    $finish;
  end
 
  initial begin
    $dumpfile("dump.vcd");
    $dumpvars;
  end
 
endmodule

dump.vcd
$date
	Tue May  5 18:59:11 2026
$end
$version
	Icarus Verilog
$end
$timescale
	1s
$end
$scope module tb $end
$var wire 16 ! RES [15:0] $end
$var wire 1 " OFLOW $end
$var wire 1 # L $end
$var wire 1 $ G $end
$var wire 1 % ERR $end
$var wire 1 & E $end
$var wire 1 ' COUT $end
$var reg 1 ( CE $end
$var reg 1 ) CIN $end
$var reg 1 * CLK $end
$var reg 4 + CMD [3:0] $end
$var reg 2 , INP_VALID [1:0] $end
$var reg 1 - MODE $end
$var reg 8 . OPA [7:0] $end
$var reg 8 / OPB [7:0] $end
$var reg 1 0 RST $end
$var integer 32 1 i [31:0] $end
$scope module dut $end
$var wire 1 ( CE $end
$var wire 1 ) CIN $end
$var wire 1 * CLK $end
$var wire 4 2 CMD [3:0] $end
$var wire 2 3 INP_VALID [1:0] $end
$var wire 1 - MODE $end
$var wire 8 4 OPA [7:0] $end
$var wire 8 5 OPB [7:0] $end
$var wire 1 0 RST $end
$var parameter 32 6 CMDWD $end
$var parameter 32 7 RW $end
$var parameter 32 8 W $end
$var reg 8 9 A [7:0] $end
$var reg 8 : B [7:0] $end
$var reg 1 ; C $end
$var reg 1 ' COUT $end
$var reg 1 & E $end
$var reg 1 % ERR $end
$var reg 1 $ G $end
$var reg 2 < IV [1:0] $end
$var reg 1 # L $end
$var reg 1 " OFLOW $end
$var reg 16 = RES [15:0] $end
$var reg 8 > SA [7:0] $end
$var reg 8 ? SB [7:0] $end
$var reg 1 @ cout $end
$var reg 1 A e $end
$var reg 1 B err $end
$var reg 1 C g $end
$var reg 1 D l $end
$var reg 1 E oflow $end
$var reg 16 F res [15:0] $end
$upscope $end
$scope task arithmetic_inputs $end
$upscope $end
$scope task logic_inputs $end
$upscope $end
$scope task reset $end
$upscope $end
$upscope $end
$enddefinitions $end
$comment Show the parameter values. $end
$dumpall
b1000 8
b11 7
b100 6
$end
#0
$dumpvars
b0 F
0E
0D
0C
0B
0A
0@
b0 ?
b0 >
b0 =
bx <
0;
b0 :
b0 9
bx 5
bx 4
bx 3
bx 2
bx 1
10
bx /
bx .
x-
bx ,
bx +
0*
x)
x(
0'
0&
0%
0$
0#
0"
b0 !
$end
#5
1*
#10
0*
#15
b101 ?
b1010 >
b11 <
x;
b101 :
b1010 9
b101 /
b101 5
b1010 .
b1010 4
b11 ,
b11 3
1(
1-
00
1*
#20
0*
#25
1;
b1111 F
1)
b0 +
b0 2
b0 1
1*
#30
0*
#35
b1111 !
b1111 =
b101 F
b1 +
b1 2
b1 1
1*
#40
0*
#45
b101 !
b101 =
b10000 F
b10 +
b10 2
b10 1
1*
#50
0*
#55
b10000 !
b10000 =
b100 F
b11 +
b11 2
b11 1
1*
#60
0*
#65
b100 !
b100 =
b1011 F
b100 +
b100 2
b100 1
1*
#70
0*
#75
b1011 !
b1011 =
b1001 F
b101 +
b101 2
b101 1
1*
#80
0*
#85
b1001 !
b1001 =
b110 F
b110 +
b110 2
b110 1
1*
#90
0*
#95
b110 !
b110 =
b100 F
b111 +
b111 2
b111 1
1*
#100
0*
#105
b100 !
b100 =
1C
b0 F
b1000 +
b1000 2
b1000 1
1*
#110
0*
#115
1$
b0 !
b0 =
b1000010 F
0C
b1001 +
b1001 2
b1001 1
1*
#120
0*
#125
b11110 F
0$
b1000010 !
b1000010 =
b100 >
b100 9
b100 .
b100 4
1*
#130
0*
#135
b11110 !
b11110 =
1*
#140
0*
#145
b101000 F
b1010 +
b1010 2
b1010 1
1*
#150
0*
#155
b111100 F
b101000 !
b101000 =
b11 ?
b1010 >
b11 :
b1010 9
b11 /
b11 5
b1010 .
b1010 4
1*
#160
0*
#165
b111100 !
b111100 =
1*
#170
0*
#175
1C
b1101 F
b1011 +
b1011 2
b1011 1
1*
#180
0*
#185
1$
b1101 !
b1101 =
1C
b111 F
b1100 +
b1100 2
b1100 1
1*
#190
0*
#195
b111 !
b111 =
0C
b0 F
b1101 +
b1101 2
b1101 1
1*
#200
0*
#205
0$
b0 !
b0 =
b101 ?
b101 :
b0 F
b0 +
b0 2
b101 /
b101 5
0-
b0 1
1*
#210
0*
#215
b11111111 F
b1 +
b1 2
b1 1
1*
#220
0*
#225
b11111111 !
b11111111 =
b1111 F
b10 +
b10 2
b10 1
1*
#230
0*
#235
b1111 !
b1111 =
b11110000 F
b11 +
b11 2
b11 1
1*
#240
0*
#245
b11110000 !
b11110000 =
b1111 F
b100 +
b100 2
b100 1
1*
#250
0*
#255
b1111 !
b1111 =
b11110000 F
b101 +
b101 2
b101 1
1*
#260
0*
#265
b11110000 !
b11110000 =
b11110101 F
b110 +
b110 2
b110 1
1*
#270
0*
#275
b11110101 !
b11110101 =
b11111010 F
b111 +
b111 2
b111 1
1*
#280
0*
#285
b11111010 !
b11111010 =
b101 F
b1000 +
b1000 2
b1000 1
1*
#290
0*
#295
b101 !
b101 =
b10100 F
b1001 +
b1001 2
b1001 1
1*
#300
0*
#305
b10100 !
b10100 =
b10 F
b1010 +
b1010 2
b1010 1
1*
#310
0*
#315
b10 !
b10 =
b1010 F
b1011 +
b1011 2
b1011 1
1*
#320
0*
#325
b1010 !
b1010 =
b1000001 F
b1100 +
b1100 2
b1100 1
1*
#330
0*
#335
b1000001 !
b1000001 =
b1010000 F
b1101 +
b1101 2
b1101 1
1*
#340
0*
#345
b1010000 !
b1010000 =
b1110 1
1*
